{
  "title": "Docker for Developers",
  "issuer": "LinkedIn Learning",
  "date": "December 2023",
  "description": "Training on using Docker for application containerization, including image creation and container management.",
  "categories": [
    "mlops"
  ],
  "verified": true,
  "link": "https://www.linkedin.com/learning/certificates/2ad9ec98113985ae1fb24fe5cbbc3db1a7a73233590d74d901f354cf760fdaf4?lipi=urn%3Ali%3Apage%3Ad_flagship3_profile_view_base_certifications_details%3B3EQveap8SVSnKDTYquyfvQ%3D%3D",
  "order": 30
}
